finalsa/dependency/injector/__init__.py
finalsa/dependency/injector/py.typed
finalsa/dependency/injector/container/__init__.py
finalsa/dependency/injector/container/container.py
finalsa/dependency/injector/container/life_cycle.py
finalsa/dependency/injector/exceptions/__init__.py
finalsa/dependency/injector/exceptions/dependency_not_found.py
finalsa/dependency/injector/exceptions/invalid_interface.py
finalsa_dependency_injector-0.1.5.data/data/LICENSE.md
finalsa_dependency_injector-0.1.5.dist-info/LICENSE.md
finalsa_dependency_injector-0.1.5.dist-info/METADATA
finalsa_dependency_injector-0.1.5.dist-info/WHEEL
finalsa_dependency_injector-0.1.5.dist-info/top_level.txt
finalsa_dependency_injector-0.1.5.dist-info/zip-safe
finalsa_dependency_injector-0.1.5.dist-info/RECORD
