Metadata-Version: 2.1
Name: finalsa-dependency-injector
Version: 0.1.5
Summary: An utils package for dependency injection .
Home-page: https://github.com/finalsa/finalsa-dependency-inyector
Author: Luis Jimenez
Author-email: luis@finalsa.com
License: MIT
Keywords: Injection,Dependency,Python,Finalsa
Classifier: Intended Audience :: Developers
Classifier: License :: OSI Approved :: BSD License
Classifier: Operating System :: OS Independent
Classifier: Topic :: Internet :: WWW/HTTP
Classifier: Programming Language :: Python :: 3
Classifier: Programming Language :: Python :: 3.7
Classifier: Programming Language :: Python :: 3.8
Classifier: Programming Language :: Python :: 3.9
Classifier: Programming Language :: Python :: 3.10
Requires-Python: >=3.10
License-File: LICENSE.md
